lets_do_dns/__init__.py
lets_do_dns/__main__.py
lets_do_dns/arguments.py
lets_do_dns/environment.py
lets_do_dns/errors.py
lets_do_dns/printer.py
lets_do_dns/acme_dns_auth/__init__.py
lets_do_dns/acme_dns_auth/authenticate.py
lets_do_dns/acme_dns_auth/command.py
lets_do_dns/acme_dns_auth/time_delay.py
lets_do_dns/dns_tools/__init__.py
lets_do_dns/dns_tools/lookup.py
lets_do_dns/do_domain/__init__.py
lets_do_dns/do_domain/resource.py
lets_do_dns/do_domain/response.py
lets_do_dns-0.10.3.dist-info/DESCRIPTION.rst
lets_do_dns-0.10.3.dist-info/METADATA
lets_do_dns-0.10.3.dist-info/RECORD
lets_do_dns-0.10.3.dist-info/WHEEL
lets_do_dns-0.10.3.dist-info/entry_points.txt
lets_do_dns-0.10.3.dist-info/metadata.json
lets_do_dns-0.10.3.dist-info/top_level.txt
