Metadata-Version: 2.0
Name: lets-do-dns
Version: 0.10.3
Summary: A letsencrypt certbot auth/cleanup hook program engineered to handle hostname ownership authentication via DigitalOcean's DNS system.
Home-page: https://github.com/jitsusama/lets-do-dns
Author: Joel Gerber
Author-email: joel@grrbrr.ca
License: Apache-2.0
Download-URL: https://github.com/jitsusama/lets-do-dns/releases/download/v0.10.3/lets-do-dns-0.10.3.tar.gz
Keywords: certbot,letsencrypt,DigitalOcean,DNS,SSL
Platform: UNKNOWN
Classifier: Development Status :: 5 - Production/Stable
Classifier: Environment :: Console
Classifier: Intended Audience :: System Administrators
Classifier: License :: OSI Approved :: Apache Software License
Classifier: Natural Language :: English
Classifier: Operating System :: OS Independent
Classifier: Programming Language :: Python :: 2.7
Classifier: Programming Language :: Python :: 3.6
Classifier: Topic :: Internet :: Name Service (DNS)
Classifier: Topic :: Security :: Cryptography
Classifier: Topic :: System :: Systems Administration
Classifier: Topic :: Utilities
Requires-Dist: dnspython
Requires-Dist: requests
